setup.cfg
setup.py
Variance.egg-info/PKG-INFO
Variance.egg-info/SOURCES.txt
Variance.egg-info/dependency_links.txt
Variance.egg-info/top_level.txt
variance/__init__.py
variance/util.py