Metadata-Version: 1.0
Name: Variance
Version: 0.2
Summary: A python configuration manager
Home-page: https://gitlab.com/cerebralpower/Variance
Author: Bill Schumacher
Author-email: bill@servernet.co
License: LGPLv3
Keywords: python configuration config variance
Platform: UNKNOWN
